{
  "group": "coincraft",
  "type": "minecraft:crafting_shaped",
  "pattern": [
    "0 2",
    "345",
    "678"
  ],
  "key": {
    "0": {
      "item": "coincraft:castironplate"
    },
    "2": {
      "item": "coincraft:castironplate"
    },
    "3": {
      "item": "coincraft:cutdiamond"
    },
    "4": {
      "item": "coincraft:castironplate"
    },
    "5": {
      "item": "coincraft:cutdiamond"
    },
    "6": {
      "item": "coincraft:cutdiamond"
    },
    "7": {
      "item": "minecraft:gold_block"
    },
    "8": {
      "item": "coincraft:cutdiamond"
    }
  },
  "result": {
    "item": "coincraft:substructure",
    "count": 1
  }
}